Workbook

Sheet Summary
A1: GTT (Gaztransport & Technigaz): three-scenario DCF
A2: Valuation date 2026-10-16. €mm unless stated. Change blue/yellow cells in 'Inputs'; everything else recalculates.
B4: Bear | C4: Base | D4: Bull | E4: Prob.-weighted
A5: New orders a year 2027-35 (LNGC-eq.) | B5: =DCF!C41 -> 35 | C5: =DCF!C82 -> 60 | D5: =DCF!C123 -> 75
A6: 2026 revenue | B6: =DCF!C13 -> 736.7 | C6: =DCF!C54 -> 736.7 | D6: =DCF!C95 -> 736.7
A7: 2030 revenue | B7: =DCF!G13 -> 522.02011 | C7: =DCF!G54 -> 785.34085 | D7: =DCF!G95 -> 948.37625
A8: 2035 revenue | B8: =DCF!L13 -> 499.21965 | C8: =DCF!L54 -> 820.38263 | D8: =DCF!L95 -> 1038.1079
A9: 2030 EBITDA margin | B9: =DCF!G17 -> 0.46012155 | C9: =DCF!G58 -> 0.62396548 | D9: =DCF!G99 -> 0.67571603
A10: Enterprise value | B10: =DCF!C33 -> 1946.2974 | C10: =DCF!C74 -> 4306.5513 | D10: =DCF!C115 -> 5879.4111
A11: Value per share (€) | B11: =DCF!C37 -> 65.628277 | C11: =DCF!C78 -> 129.30362 | D11: =DCF!C119 -> 171.73651 | E11: =SUMPRODUCT(B11:D11,B14:D14) -> 123.99301
A12: Upside / (downside) | B12: =DCF!C38 -> -0.68984746 | C12: =DCF!C79 -> -0.38892429 | D12: =DCF!C120 -> -0.1883908 | E12: =E11/Inputs!B5-1 -> -0.41402171
A13: Terminal value as % of EV | B13: =DCF!C39 -> 0.27680807 | C13: =DCF!C80 -> 0.44834261 | D13: =DCF!C121 -> 0.49504469
A14: Probability | B14: =Inputs!B70 -> 0.25 | C14: =Inputs!B71 -> 0.5 | D14: =Inputs!B72 -> 0.25
A16: Current share price (€) | B16: =Inputs!B5 -> 211.6
A17: WACC | B17: =Inputs!B19 -> 0.09628076
A18: Orders a year (2027-35) needed to justify the price | B18: ='Reverse DCF'!C7 -> 96.276916
A19: 2026 revenue vs company guidance (low end) | B19: =C6/Inputs!B76-1 -> -0.0044594595
A20: Dividend yield (FY2025 dividend €8.94) | B20: =Historical!F10/Inputs!B5 -> 0.042249527
A22: Legend: blue = input, black = formula, green = link to another sheet, yellow = key assumption.
A23: Sources: GTT press releases FY2025 (2026-02-19) and H1 2026 (2026-07-28); Yahoo Finance 2026-10-16.
A24: Personal research, not investment advice.

Sheet Inputs
A1: GTT (Gaztransport & Technigaz): inputs and scenario levers (€mm unless stated)
A2: Blue = hardcoded input. Yellow = key assumption. Black = formula. Sources in column N.
A4: Market data and capital structure
A5: Share price (€) | B5: 211.6 | N5: Yahoo Finance, close 2026-10-16
A6: Shares outstanding excl. treasury (mm) | B6: 37.067 | N6: H1 2026 press release: weighted average 37,066,945 shares
A7: Cash at 30 June 2026 | B7: 384.7 | N7: H1 2026 press release, other consolidated financial data
A8: Debt at 30 June 2026 (Danelec acquisition loan) | B8: 90 | N8: H1 2026 press release
A9: Net cash | B9: =B7-B8 -> 294.7 | N9: Formula (294.7 in the press release)
A11: Discount rate
A12: Risk-free rate (French OAT 10-year) | B12: 0.0475 | N12: Trading Economics, 2026-10-07: ~4.75% (spread over Bunds at a post-2011 high)
A13: Beta | B13: 0.9 | N13: Assumption: regression beta 0.42 (Yahoo) looks too low for a business tied to shipbuilding orders
A14: Equity risk premium | B14: 0.055 | N14: Assumption (author), Europe
A15: Cost of equity | B15: =B12+B13*B14 -> 0.097 | N15: CAPM
A16: Pre-tax cost of debt | B16: 0.04 | N16: Assumption
A17: Tax rate | B17: 0.16 | N17: H1 2026 effective rate 15.2% (37.7 / 248.2); French IP box applies to royalties
A18: Market capitalisation | B18: =B5*B6 -> 7843.3772 | N18: Formula
A19: WACC | B19: =(B18*B15+B8*B16*(1-B17))/(B18+B8) -> 0.09628076 | N19: Formula, market-value weights
A21: Revenue engine and costs
A22: Royalty per LNG-carrier-equivalent order (€mm, 2026 terms) | B22: 9.5 | N22: Derived: H1 2026 orders (65 units, ~60 LNGC-equivalent) added ~€570mm to the order-book revenue schedule
A23: Royalty escalation per year | B23: 0.02 | N23: Assumption: shipbuilding price inflation
A24: Recognition: year after order | B24: 0.2 | N24: Derived from the change in the order-book schedule Dec-25 -> Jun-26: 2027 +113, 2028 +317, 2029+ +140
A25: Recognition: second year after order | B25: 0.55 | N25: Same derivation
A26: Recognition: third year after order | B26: 0.25 | N26: Same derivation
A27: Check (must be 100%) | B27: =SUM(B24:B26) -> 1 | N27: Formula
A28: Core operating costs 2026 (excl. GTT Marine) | B28: 193 | N28: H1 2026: revenue 387.3 - EBITDA 263.6 = 123.7 of costs; ~250/yr less GTT Marine costs (~57)
A29: Core cost growth per year | B29: 0.03 | N29: Assumption: wages and R&D
A30: GTT Marine revenue 2026E | B30: 70 | N30: H1 2026: 31.8 (Danelec consolidated); assumption for H2
A31: GTT Marine EBITDA margin | B31: 0.18 | N31: H1 2026: EBITDA 5.7 on revenue 31.8
A32: Services and other revenue 2026E | B32: 22 | N32: H1 2026 services 10.8; FY2025 23.0
A33: Services growth per year | B33: 0.02 | N33: Assumption
A34: D&A per year | B34: 30 | N34: H1 2026 EBITDA - EBIT = 15.4 (includes Danelec purchase-price amortisation)
A35: Capex per year (net of subsidies) | B35: 30 | N35: Assumption: H1 2026 gross 14.5 less 12.3 subsidy; 2024 68.5 incl. headquarters
A36: Change in NWC as % of change in revenue | B36: 0.1 | N36: Assumption; FY2025 working capital rose 26.4 on +161.7 revenue
A37: H2 2026 FCF as share of modelled FY2026 FCF | B37: 0.5 | N37: Cash generated after 30 June 2026, added to net cash
A39: Revenue already secured by the order book (company schedule at 30 June 2026)
C40: 2026 | D40: 2027 | E40: 2028 | F40: 2029 | G40: 2030 | H40: 2031 | I40: 2032 | J40: 2033 | K40: 2034 | L40: 2035
A41: Core business order-book revenue | C41: 644.7 | D41: 655 | E41: 603 | F41: 221.3 | G41: 73.8 | H41: 0 | I41: 0 | J41: 0 | K41: 0 | L41: 0 | N41: H1 2026 press release: 1,853 = H2-26 300 + 2027 655 + 2028 603 + 2029+ 295. 2026 = H1 actual 344.7 + 300; 2029+ split 75/25 over 2029-30 (assumption)
A43: Scenarios: new orders in LNG-carrier equivalents (2026 column = second half only)
A44: Bear case | N44: LNG shipping is over-ordered after the 2022-26 wave and competing membrane designs win share in China: 35 orders a year.
A45: New orders (units) | C45: 15 | D45: 35 | E45: 35 | F45: 35 | G45: 35 | H45: 35 | I45: 35 | J45: 35 | K45: 35 | L45: 35
A46: GTT Marine revenue growth | C46: 0.03
A47: Terminal growth | C47: 0
A49: Base case | N49: Company's own 10-year estimate (c.550 LNG carriers + ethane, FSRU, FLNG, onshore) ~ 60 LNGC-equivalent a year.
A50: New orders (units) | C50: 30 | D50: 60 | E50: 60 | F50: 60 | G50: 60 | H50: 60 | I50: 60 | J50: 60 | K50: 60 | L50: 60
A51: GTT Marine revenue growth | C51: 0.08
A52: Terminal growth | C52: 0.015
A54: Bull case | N54: LNG demand upgrades (US, Qatar, Mozambique) and fleet renewal push orders well above the company's estimate.
A55: New orders (units) | C55: 40 | D55: 75 | E55: 75 | F55: 75 | G55: 75 | H55: 75 | I55: 75 | J55: 75 | K55: 75 | L55: 75
A56: GTT Marine revenue growth | C56: 0.12
A57: Terminal growth | C57: 0.02
A59: Reverse-DCF helper (orders = 0 from 2027; rest = base)
A60: New orders (units) | C60: =C50 -> 30 | D60: 0 | E60: 0 | F60: 0 | G60: 0 | H60: 0 | I60: 0 | J60: 0 | K60: 0 | L60: 0
A61: GTT Marine revenue growth | C61: =C51 -> 0.08
A62: Terminal growth | C62: =C52 -> 0.015
A64: Reverse-DCF helper (orders = 1 from 2027; rest = base)
A65: New orders (units) | C65: =C50 -> 30 | D65: 1 | E65: 1 | F65: 1 | G65: 1 | H65: 1 | I65: 1 | J65: 1 | K65: 1 | L65: 1
A66: GTT Marine revenue growth | C66: =C51 -> 0.08
A67: Terminal growth | C67: =C52 -> 0.015
A69: Scenario probabilities
A70: Bear | B70: 0.25 | N70: Author's judgement
A71: Base | B71: 0.5
A72: Bull | B72: 0.25
A73: Check (must be 100%) | B73: =SUM(B70:B72) -> 1
A75: For reference
A76: Company 2026 revenue guidance, low / high | B76: 740 | C76: 780 | N76: H1 2026 press release (guidance confirmed)
A77: Company 2026 EBITDA guidance, low / high | B77: 490 | C77: 530
A78: Consensus revenue 2026 / 2027 | B78: 768.3 | C78: 814.8 | N78: Yahoo Finance analyst estimates, 2026-10-16 (12 analysts; mean target €234.25)
A79: Consensus EPS 2026 / 2027 (€) | B79: 11.31 | C79: 12.11
A80: Dividend policy: payout ~80% of consolidated net income (FY2025 dividend €8.94; interim 2026 €4.30)

Sheet Historical
A1: GTT: historical figures (€mm)
A2: Sources: GTT FY2025 and H1 2026 press releases; FY2021-23 from company figures via stockanalysis.com / Yahoo Finance.
A4: €mm | B4: 2021 | C4: 2022 | D4: 2023 | E4: 2024 | F4: 2025 | G4: H1 2025 | H4: H1 2026
A5: Revenue | B5: 314.7 | C5: 307.3 | D5: 427.7 | E5: 641.4 | F5: 803 | G5: 388.7 | H5: 387.3
A6: EBITDA | C6: 163.1 | D6: 241.2 | E6: 388.1 | F6: 541.8 | G6: 264.5 | H6: 263.6
A7: Operating income (EBIT) | B7: 164.6 | C7: 152.2 | D7: 232.4 | E7: 374.3 | F7: 521.3 | G7: 257.1 | H7: 248.2
A8: Net income | B8: 134.1 | C8: 128.3 | D8: 201.4 | E8: 347.8 | F8: 413.6 | G8: 180 | H8: 210.4
A9: EPS (€) | B9: 3.62 | C9: 3.46 | D9: 5.43 | E9: 9.4 | F9: 11.2 | G9: 4.86 | H9: 5.68
A10: Dividend per share (€) | B10: 3.1 | C10: 3.1 | D10: 4.36 | E10: 7.5 | F10: 8.94 | H10: 4.3
A12: EBITDA margin | B12: =IF(B6="","",B6/B5) | C12: =IF(C6="","",C6/C5) -> 0.53075171 | D12: =IF(D6="","",D6/D5) -> 0.56394669 | E12: =IF(E6="","",E6/E5) -> 0.60508263 | F12: =IF(F6="","",F6/F5) -> 0.6747198 | G12: =IF(G6="","",G6/G5) -> 0.68047337 | H12: =IF(H6="","",H6/H5) -> 0.68060935
A13: EBIT margin | B13: =B7/B5 -> 0.52303781 | C13: =C7/C5 -> 0.49528148 | D13: =D7/D5 -> 0.54337152 | E13: =E7/E5 -> 0.5835672 | F13: =F7/F5 -> 0.64919054 | G13: =G7/G5 -> 0.66143555 | H13: =H7/H5 -> 0.64084689
A14: Payout (dividend / EPS) | B14: =IF(B10="","",B10/B9) -> 0.85635359 | C14: =IF(C10="","",C10/C9) -> 0.89595376 | D14: =IF(D10="","",D10/D9) -> 0.80294659 | E14: =IF(E10="","",E10/E9) -> 0.79787234 | F14: =IF(F10="","",F10/F9) -> 0.79821429 | G14: =IF(G10="","",G10/G9) | H14: =IF(H10="","",H10/H9) -> 0.75704225
A16: Order book (core business, excl. LNG as fuel)
B17: Units | C17: Revenue schedule (€mm)
A18: 31 Dec 2025 | B18: 288 | C18: 2026: 609 · 2027: 542 · 2028: 286 · 2029+: 155 (total 1,592)
A19: 30 Jun 2026 | B19: 306 | C19: H2-26: 300 · 2027: 655 · 2028: 603 · 2029+: 295 (total 1,853)
A20: Orders: 2022 peak 162 units; 2025: 45 (37 LNG carriers); H1 2026: 65 (56 LNG carriers)
A21: Company 10-year order estimate 2026-2035: c.550 LNG carriers, 25-40 ethane carriers, ≤10 FSRUs, ≤10 FLNGs, c.30 onshore tanks

Sheet DCF
A1: DCF by scenario (€mm). FY = calendar year. Cash flows 2027-2035 discounted from end-2026; H2 2026 cash flow added to net cash.
A3: Bear case
A4: €mm | C4: 2026 | D4: 2027 | E4: 2028 | F4: 2029 | G4: 2030 | H4: 2031 | I4: 2032 | J4: 2033 | K4: 2034 | L4: 2035
A5: Order-book revenue (already signed) | C5: =Inputs!C$41 -> 644.7 | D5: =Inputs!D$41 -> 655 | E5: =Inputs!E$41 -> 603 | F5: =Inputs!F$41 -> 221.3 | G5: =Inputs!G$41 -> 73.8 | H5: =Inputs!H$41 -> 0 | I5: =Inputs!I$41 -> 0 | J5: =Inputs!J$41 -> 0 | ... L5: =Inputs!L$41 -> 0
A6: New orders (units) | C6: =Inputs!C45 -> 15 | D6: =Inputs!D45 -> 35 | E6: =Inputs!E45 -> 35 | F6: =Inputs!F45 -> 35 | G6: =Inputs!G45 -> 35 | H6: =Inputs!H45 -> 35 | I6: =Inputs!I45 -> 35 | J6: =Inputs!J45 -> 35 | ... L6: =Inputs!L45 -> 35
A7: Royalty per unit | C7: =Inputs!$B$22*(1+Inputs!$B$23)^(2026-2026) -> 9.5 | D7: =Inputs!$B$22*(1+Inputs!$B$23)^(2027-2026) -> 9.69 | E7: =Inputs!$B$22*(1+Inputs!$B$23)^(2028-2026) -> 9.8838 | F7: =Inputs!$B$22*(1+Inputs!$B$23)^(2029-2026) -> 10.081476 | G7: =Inputs!$B$22*(1+Inputs!$B$23)^(2030-2026) -> 10.283106 | H7: =Inputs!$B$22*(1+Inputs!$B$23)^(2031-2026) -> 10.488768 | I7: =Inputs!$B$22*(1+Inputs!$B$23)^(2032-2026) -> 10.698543 | J7: =Inputs!$B$22*(1+Inputs!$B$23)^(2033-2026) -> 10.912514 | K7: =Inputs!$B$22*(1+Inputs!$B$23)^(2034-2026) -> 11.130764 | L7: =Inputs!$B$22*(1+Inputs!$B$23)^(2035-2026) -> 11.353379
A8: Value of new orders | C8: =C6*C7 -> 142.5 | D8: =D6*D7 -> 339.15 | E8: =E6*E7 -> 345.933 | F8: =F6*F7 -> 352.85166 | G8: =G6*G7 -> 359.90869 | H8: =H6*H7 -> 367.10687 | I8: =I6*I7 -> 374.449 | J8: =J6*J7 -> 381.93798 | ... L8: =L6*L7 -> 397.36828
A9: Revenue from new orders | C9: =0 -> 0 | D9: =C8*Inputs!$B$24 -> 28.5 | E9: =D8*Inputs!$B$24+C8*Inputs!$B$25 -> 146.205 | F9: =E8*Inputs!$B$24+D8*Inputs!$B$25+C8*Inputs!$B$26 -> 291.3441 | G9: =F8*Inputs!$B$24+E8*Inputs!$B$25+D8*Inputs!$B$26 -> 345.62098 | H9: =G8*Inputs!$B$24+F8*Inputs!$B$25+E8*Inputs!$B$26 -> 352.5334 | I9: =H8*Inputs!$B$24+G8*Inputs!$B$25+F8*Inputs!$B$26 -> 359.58407 | J9: =I8*Inputs!$B$24+H8*Inputs!$B$25+G8*Inputs!$B$26 -> 366.77575 | K9: =J8*Inputs!$B$24+I8*Inputs!$B$25+H8*Inputs!$B$26 -> 374.11127 | L9: =K8*Inputs!$B$24+J8*Inputs!$B$25+I8*Inputs!$B$26 -> 381.59349
A10: Core containment revenue | C10: =C5+C9 -> 644.7 | D10: =D5+D9 -> 683.5 | E10: =E5+E9 -> 749.205 | F10: =F5+F9 -> 512.6441 | G10: =G5+G9 -> 419.42098 | H10: =H5+H9 -> 352.5334 | I10: =I5+I9 -> 359.58407 | J10: =J5+J9 -> 366.77575 | ... L10: =L5+L9 -> 381.59349
A11: GTT Marine revenue | C11: =Inputs!$B$30 -> 70 | D11: =C11*(1+Inputs!$C$46) -> 72.1 | E11: =D11*(1+Inputs!$C$46) -> 74.263 | F11: =E11*(1+Inputs!$C$46) -> 76.49089 | G11: =F11*(1+Inputs!$C$46) -> 78.785617 | H11: =G11*(1+Inputs!$C$46) -> 81.149185 | I11: =H11*(1+Inputs!$C$46) -> 83.583661 | J11: =I11*(1+Inputs!$C$46) -> 86.091171 | K11: =J11*(1+Inputs!$C$46) -> 88.673906 | L11: =K11*(1+Inputs!$C$46) -> 91.334123
A12: Services and other | C12: =Inputs!$B$32*(1+Inputs!$B$33)^(2026-2026) -> 22 | D12: =Inputs!$B$32*(1+Inputs!$B$33)^(2027-2026) -> 22.44 | E12: =Inputs!$B$32*(1+Inputs!$B$33)^(2028-2026) -> 22.8888 | F12: =Inputs!$B$32*(1+Inputs!$B$33)^(2029-2026) -> 23.346576 | G12: =Inputs!$B$32*(1+Inputs!$B$33)^(2030-2026) -> 23.813508 | H12: =Inputs!$B$32*(1+Inputs!$B$33)^(2031-2026) -> 24.289778 | I12: =Inputs!$B$32*(1+Inputs!$B$33)^(2032-2026) -> 24.775573 | J12: =Inputs!$B$32*(1+Inputs!$B$33)^(2033-2026) -> 25.271085 | K12: =Inputs!$B$32*(1+Inputs!$B$33)^(2034-2026) -> 25.776506 | L12: =Inputs!$B$32*(1+Inputs!$B$33)^(2035-2026) -> 26.292037
A13: Total revenue | C13: =C10+C11+C12 -> 736.7 | D13: =D10+D11+D12 -> 778.04 | E13: =E10+E11+E12 -> 846.3568 | F13: =F10+F11+F12 -> 612.48157 | G13: =G10+G11+G12 -> 522.02011 | H13: =H10+H11+H12 -> 457.97236 | I13: =I10+I11+I12 -> 467.9433 | J13: =J10+J11+J12 -> 478.13801 | ... L13: =L10+L11+L12 -> 499.21965
A14: Core operating costs | C14: =-Inputs!$B$28*(1+Inputs!$B$29)^(2026-2026) -> -193 | D14: =-Inputs!$B$28*(1+Inputs!$B$29)^(2027-2026) -> -198.79 | E14: =-Inputs!$B$28*(1+Inputs!$B$29)^(2028-2026) -> -204.7537 | F14: =-Inputs!$B$28*(1+Inputs!$B$29)^(2029-2026) -> -210.89631 | G14: =-Inputs!$B$28*(1+Inputs!$B$29)^(2030-2026) -> -217.2232 | H14: =-Inputs!$B$28*(1+Inputs!$B$29)^(2031-2026) -> -223.7399 | I14: =-Inputs!$B$28*(1+Inputs!$B$29)^(2032-2026) -> -230.45209 | J14: =-Inputs!$B$28*(1+Inputs!$B$29)^(2033-2026) -> -237.36566 | K14: =-Inputs!$B$28*(1+Inputs!$B$29)^(2034-2026) -> -244.48663 | L14: =-Inputs!$B$28*(1+Inputs!$B$29)^(2035-2026) -> -251.82122
A15: GTT Marine costs | C15: =-C11*(1-Inputs!$B$31) -> -57.4 | D15: =-D11*(1-Inputs!$B$31) -> -59.122 | E15: =-E11*(1-Inputs!$B$31) -> -60.89566 | F15: =-F11*(1-Inputs!$B$31) -> -62.72253 | G15: =-G11*(1-Inputs!$B$31) -> -64.604206 | H15: =-H11*(1-Inputs!$B$31) -> -66.542332 | I15: =-I11*(1-Inputs!$B$31) -> -68.538602 | J15: =-J11*(1-Inputs!$B$31) -> -70.59476 | ... L15: =-L11*(1-Inputs!$B$31) -> -74.893981
A16: EBITDA | C16: =C13+C14+C15 -> 486.3 | D16: =D13+D14+D15 -> 520.128 | E16: =E13+E14+E15 -> 580.70744 | F16: =F13+F14+F15 -> 338.86273 | G16: =G13+G14+G15 -> 240.1927 | H16: =H13+H14+H15 -> 167.69014 | I16: =I13+I14+I15 -> 168.95261 | J16: =J13+J14+J15 -> 170.17759 | ... L16: =L13+L14+L15 -> 172.50445
A17: EBITDA margin | C17: =C16/C13 -> 0.66010588 | D17: =D16/D13 -> 0.66851062 | E17: =E16/E13 -> 0.68612604 | F17: =F16/F13 -> 0.55326192 | G17: =G16/G13 -> 0.46012155 | H17: =H16/H13 -> 0.36615776 | I17: =I16/I13 -> 0.36105359 | J17: =J16/J13 -> 0.3559173 | ... L17: =L16/L13 -> 0.34554819
A18: D&A | C18: =-Inputs!$B$34 -> -30 | D18: =-Inputs!$B$34 -> -30 | E18: =-Inputs!$B$34 -> -30 | F18: =-Inputs!$B$34 -> -30 | G18: =-Inputs!$B$34 -> -30 | H18: =-Inputs!$B$34 -> -30 | I18: =-Inputs!$B$34 -> -30 | J18: =-Inputs!$B$34 -> -30 | ... L18: =-Inputs!$B$34 -> -30
A19: EBIT | C19: =C16+C18 -> 456.3 | D19: =D16+D18 -> 490.128 | E19: =E16+E18 -> 550.70744 | F19: =F16+F18 -> 308.86273 | G19: =G16+G18 -> 210.1927 | H19: =H16+H18 -> 137.69014 | I19: =I16+I18 -> 138.95261 | J19: =J16+J18 -> 140.17759 | ... L19: =L16+L18 -> 142.50445
A20: Taxes | C20: =-C19*Inputs!$B$17 -> -73.008 | D20: =-D19*Inputs!$B$17 -> -78.42048 | E20: =-E19*Inputs!$B$17 -> -88.11319 | F20: =-F19*Inputs!$B$17 -> -49.418036 | G20: =-G19*Inputs!$B$17 -> -33.630832 | H20: =-H19*Inputs!$B$17 -> -22.030422 | I20: =-I19*Inputs!$B$17 -> -22.232417 | J20: =-J19*Inputs!$B$17 -> -22.428414 | ... L20: =-L19*Inputs!$B$17 -> -22.800711
A21: NOPAT | C21: =C19+C20 -> 383.292 | D21: =D19+D20 -> 411.70752 | E21: =E19+E20 -> 462.59425 | F21: =F19+F20 -> 259.44469 | G21: =G19+G20 -> 176.56187 | H21: =H19+H20 -> 115.65971 | I21: =I19+I20 -> 116.72019 | J21: =J19+J20 -> 117.74918 | ... L21: =L19+L20 -> 119.70373
A22: Capex | C22: =-Inputs!$B$35 -> -30 | D22: =-Inputs!$B$35 -> -30 | E22: =-Inputs!$B$35 -> -30 | F22: =-Inputs!$B$35 -> -30 | G22: =-Inputs!$B$35 -> -30 | H22: =-Inputs!$B$35 -> -30 | I22: =-Inputs!$B$35 -> -30 | J22: =-Inputs!$B$35 -> -30 | ... L22: =-Inputs!$B$35 -> -30
A23: Change in NWC | C23: =0 -> 0 | D23: =-Inputs!$B$36*(D13-C13) -> -4.134 | E23: =-Inputs!$B$36*(E13-D13) -> -6.83168 | F23: =-Inputs!$B$36*(F13-E13) -> 23.387523 | G23: =-Inputs!$B$36*(G13-F13) -> 9.046146 | H23: =-Inputs!$B$36*(H13-G13) -> 6.4047742 | I23: =-Inputs!$B$36*(I13-H13) -> -0.99709391 | J23: =-Inputs!$B$36*(J13-I13) -> -1.0194703 | K23: =-Inputs!$B$36*(K13-J13) -> -1.0423672 | L23: =-Inputs!$B$36*(L13-K13) -> -1.0657973
A24: Free cash flow | C24: =C21-C18+C22+C23 -> 383.292 | D24: =D21-D18+D22+D23 -> 407.57352 | E24: =E21-E18+E22+E23 -> 455.76257 | F24: =F21-F18+F22+F23 -> 282.83221 | G24: =G21-G18+G22+G23 -> 185.60801 | H24: =H21-H18+H22+H23 -> 122.06449 | I24: =I21-I18+I22+I23 -> 115.7231 | J24: =J21-J18+J22+J23 -> 116.72971 | ... L24: =L21-L18+L22+L23 -> 118.63794
A25: Discount period (years) | D25: 1 | E25: 2 | F25: 3 | G25: 4 | H25: 5 | I25: 6 | J25: 7 | K25: 8 | L25: 9
A26: Discount factor | D26: =1/(1+Inputs!$B$19)^D25 -> 0.91217509 | E26: =1/(1+Inputs!$B$19)^E25 -> 0.83206339 | F26: =1/(1+Inputs!$B$19)^F25 -> 0.7589875 | G26: =1/(1+Inputs!$B$19)^G25 -> 0.69232949 | H26: =1/(1+Inputs!$B$19)^H25 -> 0.63152571 | I26: =1/(1+Inputs!$B$19)^I25 -> 0.57606202 | J26: =1/(1+Inputs!$B$19)^J25 -> 0.52546943 | K26: =1/(1+Inputs!$B$19)^K25 -> 0.47932012 | L26: =1/(1+Inputs!$B$19)^L25 -> 0.43722388
A27: PV of FCF | D27: =D24*D26 -> 371.77841 | E27: =E24*E26 -> 379.22335 | F27: =F24*F26 -> 214.66611 | G27: =G24*G26 -> 128.5019 | H27: =H24*H26 -> 77.086863 | I27: =I24*I26 -> 66.663682 | J27: =J24*J26 -> 61.337892 | K27: =K24*K26 -> 56.41698 | L27: =L24*L26 -> 51.871339
A29: Terminal growth | C29: =Inputs!C47 -> 0
A30: Terminal value at 2035 | C30: =L24*(1+C29)/(Inputs!$B$19-C29) -> 1232.2081
A31: PV of terminal value | C31: =C30*L26 -> 538.75082
A32: Sum of PV of FCF (2027-35) | C32: =SUM(D27:L27) -> 1407.5465
A33: Enterprise value | C33: =C31+C32 -> 1946.2974
A34: + Net cash at 30 June 2026 | C34: =Inputs!$B$9 -> 294.7
A35: + H2 2026 free cash flow | C35: =C24*Inputs!$B$37 -> 191.646
A36: Equity value | C36: =SUM(C33:C35) -> 2432.6434
A37: Value per share (€) | C37: =C36/Inputs!$B$6 -> 65.628277
A38: Upside / (downside) vs price | C38: =C37/Inputs!$B$5-1 -> -0.68984746
A39: Terminal value as % of EV | C39: =C31/C33 -> 0.27680807
A40: Implied P/E on 2027 NOPAT | C40: =Inputs!$B$18/D21 -> 19.050848
A41: Average new orders 2027-35 (units/yr) | C41: =AVERAGE(D6:L6) -> 35
A44: Base case
A45: €mm | C45: 2026 | D45: 2027 | E45: 2028 | F45: 2029 | G45: 2030 | H45: 2031 | I45: 2032 | J45: 2033 | K45: 2034 | L45: 2035
A46: Order-book revenue (already signed) | C46: =Inputs!C$41 -> 644.7 | D46: =Inputs!D$41 -> 655 | E46: =Inputs!E$41 -> 603 | F46: =Inputs!F$41 -> 221.3 | G46: =Inputs!G$41 -> 73.8 | H46: =Inputs!H$41 -> 0 | I46: =Inputs!I$41 -> 0 | J46: =Inputs!J$41 -> 0 | ... L46: =Inputs!L$41 -> 0
A47: New orders (units) | C47: =Inputs!C50 -> 30 | D47: =Inputs!D50 -> 60 | E47: =Inputs!E50 -> 60 | F47: =Inputs!F50 -> 60 | G47: =Inputs!G50 -> 60 | H47: =Inputs!H50 -> 60 | I47: =Inputs!I50 -> 60 | J47: =Inputs!J50 -> 60 | ... L47: =Inputs!L50 -> 60
A48: Royalty per unit | C48: =Inputs!$B$22*(1+Inputs!$B$23)^(2026-2026) -> 9.5 | D48: =Inputs!$B$22*(1+Inputs!$B$23)^(2027-2026) -> 9.69 | E48: =Inputs!$B$22*(1+Inputs!$B$23)^(2028-2026) -> 9.8838 | F48: =Inputs!$B$22*(1+Inputs!$B$23)^(2029-2026) -> 10.081476 | G48: =Inputs!$B$22*(1+Inputs!$B$23)^(2030-2026) -> 10.283106 | H48: =Inputs!$B$22*(1+Inputs!$B$23)^(2031-2026) -> 10.488768 | I48: =Inputs!$B$22*(1+Inputs!$B$23)^(2032-2026) -> 10.698543 | J48: =Inputs!$B$22*(1+Inputs!$B$23)^(2033-2026) -> 10.912514 | K48: =Inputs!$B$22*(1+Inputs!$B$23)^(2034-2026) -> 11.130764 | L48: =Inputs!$B$22*(1+Inputs!$B$23)^(2035-2026) -> 11.353379
A49: Value of new orders | C49: =C47*C48 -> 285 | D49: =D47*D48 -> 581.4 | E49: =E47*E48 -> 593.028 | F49: =F47*F48 -> 604.88856 | G49: =G47*G48 -> 616.98633 | H49: =H47*H48 -> 629.32606 | I49: =I47*I48 -> 641.91258 | J49: =J47*J48 -> 654.75083 | ... L49: =L47*L48 -> 681.20276
A50: Revenue from new orders | C50: =0 -> 0 | D50: =C49*Inputs!$B$24 -> 57 | E50: =D49*Inputs!$B$24+C49*Inputs!$B$25 -> 273.03 | F50: =E49*Inputs!$B$24+D49*Inputs!$B$25+C49*Inputs!$B$26 -> 509.6256 | G50: =F49*Inputs!$B$24+E49*Inputs!$B$25+D49*Inputs!$B$26 -> 592.49311 | H50: =G49*Inputs!$B$24+F49*Inputs!$B$25+E49*Inputs!$B$26 -> 604.34297 | I50: =H49*Inputs!$B$24+G49*Inputs!$B$25+F49*Inputs!$B$26 -> 616.42983 | J50: =I49*Inputs!$B$24+H49*Inputs!$B$25+G49*Inputs!$B$26 -> 628.75843 | K50: =J49*Inputs!$B$24+I49*Inputs!$B$25+H49*Inputs!$B$26 -> 641.3336 | L50: =K49*Inputs!$B$24+J49*Inputs!$B$25+I49*Inputs!$B$26 -> 654.16027
A51: Core containment revenue | C51: =C46+C50 -> 644.7 | D51: =D46+D50 -> 712 | E51: =E46+E50 -> 876.03 | F51: =F46+F50 -> 730.9256 | G51: =G46+G50 -> 666.29311 | H51: =H46+H50 -> 604.34297 | I51: =I46+I50 -> 616.42983 | J51: =J46+J50 -> 628.75843 | ... L51: =L46+L50 -> 654.16027
A52: GTT Marine revenue | C52: =Inputs!$B$30 -> 70 | D52: =C52*(1+Inputs!$C$51) -> 75.6 | E52: =D52*(1+Inputs!$C$51) -> 81.648 | F52: =E52*(1+Inputs!$C$51) -> 88.17984 | G52: =F52*(1+Inputs!$C$51) -> 95.234227 | H52: =G52*(1+Inputs!$C$51) -> 102.85297 | I52: =H52*(1+Inputs!$C$51) -> 111.0812 | J52: =I52*(1+Inputs!$C$51) -> 119.9677 | K52: =J52*(1+Inputs!$C$51) -> 129.56511 | L52: =K52*(1+Inputs!$C$51) -> 139.93032
A53: Services and other | C53: =Inputs!$B$32*(1+Inputs!$B$33)^(2026-2026) -> 22 | D53: =Inputs!$B$32*(1+Inputs!$B$33)^(2027-2026) -> 22.44 | E53: =Inputs!$B$32*(1+Inputs!$B$33)^(2028-2026) -> 22.8888 | F53: =Inputs!$B$32*(1+Inputs!$B$33)^(2029-2026) -> 23.346576 | G53: =Inputs!$B$32*(1+Inputs!$B$33)^(2030-2026) -> 23.813508 | H53: =Inputs!$B$32*(1+Inputs!$B$33)^(2031-2026) -> 24.289778 | I53: =Inputs!$B$32*(1+Inputs!$B$33)^(2032-2026) -> 24.775573 | J53: =Inputs!$B$32*(1+Inputs!$B$33)^(2033-2026) -> 25.271085 | K53: =Inputs!$B$32*(1+Inputs!$B$33)^(2034-2026) -> 25.776506 | L53: =Inputs!$B$32*(1+Inputs!$B$33)^(2035-2026) -> 26.292037
A54: Total revenue | C54: =C51+C52+C53 -> 736.7 | D54: =D51+D52+D53 -> 810.04 | E54: =E51+E52+E53 -> 980.5668 | F54: =F51+F52+F53 -> 842.45202 | G54: =G51+G52+G53 -> 785.34085 | H54: =H51+H52+H53 -> 731.48572 | I54: =I51+I52+I53 -> 752.28661 | J54: =J51+J52+J53 -> 773.99721 | ... L54: =L51+L52+L53 -> 820.38263
A55: Core operating costs | C55: =-Inputs!$B$28*(1+Inputs!$B$29)^(2026-2026) -> -193 | D55: =-Inputs!$B$28*(1+Inputs!$B$29)^(2027-2026) -> -198.79 | E55: =-Inputs!$B$28*(1+Inputs!$B$29)^(2028-2026) -> -204.7537 | F55: =-Inputs!$B$28*(1+Inputs!$B$29)^(2029-2026) -> -210.89631 | G55: =-Inputs!$B$28*(1+Inputs!$B$29)^(2030-2026) -> -217.2232 | H55: =-Inputs!$B$28*(1+Inputs!$B$29)^(2031-2026) -> -223.7399 | I55: =-Inputs!$B$28*(1+Inputs!$B$29)^(2032-2026) -> -230.45209 | J55: =-Inputs!$B$28*(1+Inputs!$B$29)^(2033-2026) -> -237.36566 | K55: =-Inputs!$B$28*(1+Inputs!$B$29)^(2034-2026) -> -244.48663 | L55: =-Inputs!$B$28*(1+Inputs!$B$29)^(2035-2026) -> -251.82122
A56: GTT Marine costs | C56: =-C52*(1-Inputs!$B$31) -> -57.4 | D56: =-D52*(1-Inputs!$B$31) -> -61.992 | E56: =-E52*(1-Inputs!$B$31) -> -66.95136 | F56: =-F52*(1-Inputs!$B$31) -> -72.307469 | G56: =-G52*(1-Inputs!$B$31) -> -78.092066 | H56: =-H52*(1-Inputs!$B$31) -> -84.339432 | I56: =-I52*(1-Inputs!$B$31) -> -91.086586 | J56: =-J52*(1-Inputs!$B$31) -> -98.373513 | ... L56: =-L52*(1-Inputs!$B$31) -> -114.74287
A57: EBITDA | C57: =C54+C55+C56 -> 486.3 | D57: =D54+D55+D56 -> 549.258 | E57: =E54+E55+E56 -> 708.86174 | F57: =F54+F55+F56 -> 559.24824 | G57: =G54+G55+G56 -> 490.02558 | H57: =H54+H55+H56 -> 423.40639 | I57: =I54+I55+I56 -> 430.74793 | J57: =J54+J55+J56 -> 438.25804 | ... L57: =L54+L55+L56 -> 453.81854
A58: EBITDA margin | C58: =C57/C54 -> 0.66010588 | D58: =D57/D54 -> 0.67806281 | E58: =E57/E54 -> 0.7229102 | F58: =F57/F54 -> 0.66383393 | G58: =G57/G54 -> 0.62396548 | H58: =H57/H54 -> 0.5788307 | I58: =I57/I54 -> 0.57258487 | J58: =J57/J54 -> 0.5662269 | ... L58: =L57/L54 -> 0.55317912
A59: D&A | C59: =-Inputs!$B$34 -> -30 | D59: =-Inputs!$B$34 -> -30 | E59: =-Inputs!$B$34 -> -30 | F59: =-Inputs!$B$34 -> -30 | G59: =-Inputs!$B$34 -> -30 | H59: =-Inputs!$B$34 -> -30 | I59: =-Inputs!$B$34 -> -30 | J59: =-Inputs!$B$34 -> -30 | ... L59: =-Inputs!$B$34 -> -30
A60: EBIT | C60: =C57+C59 -> 456.3 | D60: =D57+D59 -> 519.258 | E60: =E57+E59 -> 678.86174 | F60: =F57+F59 -> 529.24824 | G60: =G57+G59 -> 460.02558 | H60: =H57+H59 -> 393.40639 | I60: =I57+I59 -> 400.74793 | J60: =J57+J59 -> 408.25804 | ... L60: =L57+L59 -> 423.81854
A61: Taxes | C61: =-C60*Inputs!$B$17 -> -73.008 | D61: =-D60*Inputs!$B$17 -> -83.08128 | E61: =-E60*Inputs!$B$17 -> -108.61788 | F61: =-F60*Inputs!$B$17 -> -84.679718 | G61: =-G60*Inputs!$B$17 -> -73.604093 | H61: =-H60*Inputs!$B$17 -> -62.945022 | I61: =-I60*Inputs!$B$17 -> -64.119669 | J61: =-J60*Inputs!$B$17 -> -65.321287 | ... L61: =-L60*Inputs!$B$17 -> -67.810967
A62: NOPAT | C62: =C60+C61 -> 383.292 | D62: =D60+D61 -> 436.17672 | E62: =E60+E61 -> 570.24386 | F62: =F60+F61 -> 444.56852 | G62: =G60+G61 -> 386.42149 | H62: =H60+H61 -> 330.46137 | I62: =I60+I61 -> 336.62826 | J62: =J60+J61 -> 342.93676 | ... L62: =L60+L61 -> 356.00757
A63: Capex | C63: =-Inputs!$B$35 -> -30 | D63: =-Inputs!$B$35 -> -30 | E63: =-Inputs!$B$35 -> -30 | F63: =-Inputs!$B$35 -> -30 | G63: =-Inputs!$B$35 -> -30 | H63: =-Inputs!$B$35 -> -30 | I63: =-Inputs!$B$35 -> -30 | J63: =-Inputs!$B$35 -> -30 | ... L63: =-Inputs!$B$35 -> -30
A64: Change in NWC | C64: =0 -> 0 | D64: =-Inputs!$B$36*(D54-C54) -> -7.334 | E64: =-Inputs!$B$36*(E54-D54) -> -17.05268 | F64: =-Inputs!$B$36*(F54-E54) -> 13.811478 | G64: =-Inputs!$B$36*(G54-F54) -> 5.7111169 | H64: =-Inputs!$B$36*(H54-G54) -> 5.3855129 | I64: =-Inputs!$B$36*(I54-H54) -> -2.0800892 | J64: =-Inputs!$B$36*(J54-I54) -> -2.1710604 | K64: =-Inputs!$B$36*(K54-J54) -> -2.2678006 | L64: =-Inputs!$B$36*(L54-K54) -> -2.3707411
A65: Free cash flow | C65: =C62-C59+C63+C64 -> 383.292 | D65: =D62-D59+D63+D64 -> 428.84272 | E65: =E62-E59+E63+E64 -> 553.19118 | F65: =F62-F59+F63+F64 -> 458.38 | G65: =G62-G59+G63+G64 -> 392.1326 | H65: =H62-H59+H63+H64 -> 335.84688 | I65: =I62-I59+I63+I64 -> 334.54817 | J65: =J62-J59+J63+J64 -> 340.7657 | ... L65: =L62-L59+L63+L64 -> 353.63683
A66: Discount period (years) | D66: 1 | E66: 2 | F66: 3 | G66: 4 | H66: 5 | I66: 6 | J66: 7 | K66: 8 | L66: 9
A67: Discount factor | D67: =1/(1+Inputs!$B$19)^D66 -> 0.91217509 | E67: =1/(1+Inputs!$B$19)^E66 -> 0.83206339 | F67: =1/(1+Inputs!$B$19)^F66 -> 0.7589875 | G67: =1/(1+Inputs!$B$19)^G66 -> 0.69232949 | H67: =1/(1+Inputs!$B$19)^H66 -> 0.63152571 | I67: =1/(1+Inputs!$B$19)^I66 -> 0.57606202 | J67: =1/(1+Inputs!$B$19)^J66 -> 0.52546943 | K67: =1/(1+Inputs!$B$19)^K66 -> 0.47932012 | L67: =1/(1+Inputs!$B$19)^L66 -> 0.43722388
A68: PV of FCF | D68: =D65*D67 -> 391.17965 | E68: =E65*E67 -> 460.29013 | F68: =F65*F67 -> 347.90469 | G68: =G65*G67 -> 271.48497 | H68: =H65*H67 -> 212.09594 | I68: =I65*I67 -> 192.7205 | J68: =J65*J67 -> 179.06196 | K68: =K65*K67 -> 166.38456 | L68: =L65*L67 -> 154.61847
A70: Terminal growth | C70: =Inputs!C52 -> 0.015
A71: Terminal value at 2035 | C71: =L65*(1+C70)/(Inputs!$B$19-C70) -> 4416.0683
A72: PV of terminal value | C72: =C71*L67 -> 1930.8105
A73: Sum of PV of FCF (2027-35) | C73: =SUM(D68:L68) -> 2375.7408
A74: Enterprise value | C74: =C72+C73 -> 4306.5513
A75: + Net cash at 30 June 2026 | C75: =Inputs!$B$9 -> 294.7
A76: + H2 2026 free cash flow | C76: =C65*Inputs!$B$37 -> 191.646
A77: Equity value | C77: =SUM(C74:C76) -> 4792.8973
A78: Value per share (€) | C78: =C77/Inputs!$B$6 -> 129.30362
A79: Upside / (downside) vs price | C79: =C78/Inputs!$B$5-1 -> -0.38892429
A80: Terminal value as % of EV | C80: =C72/C74 -> 0.44834261
A81: Implied P/E on 2027 NOPAT | C81: =Inputs!$B$18/D62 -> 17.982109
A82: Average new orders 2027-35 (units/yr) | C82: =AVERAGE(D47:L47) -> 60
A85: Bull case
A86: €mm | C86: 2026 | D86: 2027 | E86: 2028 | F86: 2029 | G86: 2030 | H86: 2031 | I86: 2032 | J86: 2033 | K86: 2034 | L86: 2035
A87: Order-book revenue (already signed) | C87: =Inputs!C$41 -> 644.7 | D87: =Inputs!D$41 -> 655 | E87: =Inputs!E$41 -> 603 | F87: =Inputs!F$41 -> 221.3 | G87: =Inputs!G$41 -> 73.8 | H87: =Inputs!H$41 -> 0 | I87: =Inputs!I$41 -> 0 | J87: =Inputs!J$41 -> 0 | ... L87: =Inputs!L$41 -> 0
A88: New orders (units) | C88: =Inputs!C55 -> 40 | D88: =Inputs!D55 -> 75 | E88: =Inputs!E55 -> 75 | F88: =Inputs!F55 -> 75 | G88: =Inputs!G55 -> 75 | H88: =Inputs!H55 -> 75 | I88: =Inputs!I55 -> 75 | J88: =Inputs!J55 -> 75 | ... L88: =Inputs!L55 -> 75
A89: Royalty per unit | C89: =Inputs!$B$22*(1+Inputs!$B$23)^(2026-2026) -> 9.5 | D89: =Inputs!$B$22*(1+Inputs!$B$23)^(2027-2026) -> 9.69 | E89: =Inputs!$B$22*(1+Inputs!$B$23)^(2028-2026) -> 9.8838 | F89: =Inputs!$B$22*(1+Inputs!$B$23)^(2029-2026) -> 10.081476 | G89: =Inputs!$B$22*(1+Inputs!$B$23)^(2030-2026) -> 10.283106 | H89: =Inputs!$B$22*(1+Inputs!$B$23)^(2031-2026) -> 10.488768 | I89: =Inputs!$B$22*(1+Inputs!$B$23)^(2032-2026) -> 10.698543 | J89: =Inputs!$B$22*(1+Inputs!$B$23)^(2033-2026) -> 10.912514 | K89: =Inputs!$B$22*(1+Inputs!$B$23)^(2034-2026) -> 11.130764 | L89: =Inputs!$B$22*(1+Inputs!$B$23)^(2035-2026) -> 11.353379
A90: Value of new orders | C90: =C88*C89 -> 380 | D90: =D88*D89 -> 726.75 | E90: =E88*E89 -> 741.285 | F90: =F88*F89 -> 756.1107 | G90: =G88*G89 -> 771.23291 | H90: =H88*H89 -> 786.65757 | I90: =I88*I89 -> 802.39072 | J90: =J88*J89 -> 818.43854 | ... L90: =L88*L89 -> 851.50346
A91: Revenue from new orders | C91: =0 -> 0 | D91: =C90*Inputs!$B$24 -> 76 | E91: =D90*Inputs!$B$24+C90*Inputs!$B$25 -> 354.35 | F91: =E90*Inputs!$B$24+D90*Inputs!$B$25+C90*Inputs!$B$26 -> 642.9695 | G91: =F90*Inputs!$B$24+E90*Inputs!$B$25+D90*Inputs!$B$26 -> 740.61639 | H91: =G90*Inputs!$B$24+F90*Inputs!$B$25+E90*Inputs!$B$26 -> 755.42872 | I91: =H90*Inputs!$B$24+G90*Inputs!$B$25+F90*Inputs!$B$26 -> 770.53729 | J91: =I90*Inputs!$B$24+H90*Inputs!$B$25+G90*Inputs!$B$26 -> 785.94804 | K91: =J90*Inputs!$B$24+I90*Inputs!$B$25+H90*Inputs!$B$26 -> 801.667 | L91: =K90*Inputs!$B$24+J90*Inputs!$B$25+I90*Inputs!$B$26 -> 817.70034
A92: Core containment revenue | C92: =C87+C91 -> 644.7 | D92: =D87+D91 -> 731 | E92: =E87+E91 -> 957.35 | F92: =F87+F91 -> 864.2695 | G92: =G87+G91 -> 814.41639 | H92: =H87+H91 -> 755.42872 | I92: =I87+I91 -> 770.53729 | J92: =J87+J91 -> 785.94804 | ... L92: =L87+L91 -> 817.70034
A93: GTT Marine revenue | C93: =Inputs!$B$30 -> 70 | D93: =C93*(1+Inputs!$C$56) -> 78.4 | E93: =D93*(1+Inputs!$C$56) -> 87.808 | F93: =E93*(1+Inputs!$C$56) -> 98.34496 | G93: =F93*(1+Inputs!$C$56) -> 110.14636 | H93: =G93*(1+Inputs!$C$56) -> 123.36392 | I93: =H93*(1+Inputs!$C$56) -> 138.16759 | J93: =I93*(1+Inputs!$C$56) -> 154.7477 | K93: =J93*(1+Inputs!$C$56) -> 173.31742 | L93: =K93*(1+Inputs!$C$56) -> 194.11551
A94: Services and other | C94: =Inputs!$B$32*(1+Inputs!$B$33)^(2026-2026) -> 22 | D94: =Inputs!$B$32*(1+Inputs!$B$33)^(2027-2026) -> 22.44 | E94: =Inputs!$B$32*(1+Inputs!$B$33)^(2028-2026) -> 22.8888 | F94: =Inputs!$B$32*(1+Inputs!$B$33)^(2029-2026) -> 23.346576 | G94: =Inputs!$B$32*(1+Inputs!$B$33)^(2030-2026) -> 23.813508 | H94: =Inputs!$B$32*(1+Inputs!$B$33)^(2031-2026) -> 24.289778 | I94: =Inputs!$B$32*(1+Inputs!$B$33)^(2032-2026) -> 24.775573 | J94: =Inputs!$B$32*(1+Inputs!$B$33)^(2033-2026) -> 25.271085 | K94: =Inputs!$B$32*(1+Inputs!$B$33)^(2034-2026) -> 25.776506 | L94: =Inputs!$B$32*(1+Inputs!$B$33)^(2035-2026) -> 26.292037
A95: Total revenue | C95: =C92+C93+C94 -> 736.7 | D95: =D92+D93+D94 -> 831.84 | E95: =E92+E93+E94 -> 1068.0468 | F95: =F92+F93+F94 -> 985.96104 | G95: =G92+G93+G94 -> 948.37625 | H95: =H92+H93+H94 -> 903.08241 | I95: =I92+I93+I94 -> 933.48045 | J95: =J92+J93+J94 -> 965.96682 | ... L95: =L92+L93+L94 -> 1038.1079
A96: Core operating costs | C96: =-Inputs!$B$28*(1+Inputs!$B$29)^(2026-2026) -> -193 | D96: =-Inputs!$B$28*(1+Inputs!$B$29)^(2027-2026) -> -198.79 | E96: =-Inputs!$B$28*(1+Inputs!$B$29)^(2028-2026) -> -204.7537 | F96: =-Inputs!$B$28*(1+Inputs!$B$29)^(2029-2026) -> -210.89631 | G96: =-Inputs!$B$28*(1+Inputs!$B$29)^(2030-2026) -> -217.2232 | H96: =-Inputs!$B$28*(1+Inputs!$B$29)^(2031-2026) -> -223.7399 | I96: =-Inputs!$B$28*(1+Inputs!$B$29)^(2032-2026) -> -230.45209 | J96: =-Inputs!$B$28*(1+Inputs!$B$29)^(2033-2026) -> -237.36566 | K96: =-Inputs!$B$28*(1+Inputs!$B$29)^(2034-2026) -> -244.48663 | L96: =-Inputs!$B$28*(1+Inputs!$B$29)^(2035-2026) -> -251.82122
A97: GTT Marine costs | C97: =-C93*(1-Inputs!$B$31) -> -57.4 | D97: =-D93*(1-Inputs!$B$31) -> -64.288 | E97: =-E93*(1-Inputs!$B$31) -> -72.00256 | F97: =-F93*(1-Inputs!$B$31) -> -80.642867 | G97: =-G93*(1-Inputs!$B$31) -> -90.320011 | H97: =-H93*(1-Inputs!$B$31) -> -101.15841 | I97: =-I93*(1-Inputs!$B$31) -> -113.29742 | J97: =-J93*(1-Inputs!$B$31) -> -126.89311 | ... L97: =-L93*(1-Inputs!$B$31) -> -159.17472
A98: EBITDA | C98: =C95+C96+C97 -> 486.3 | D98: =D95+D96+D97 -> 568.762 | E98: =E95+E96+E97 -> 791.29054 | F98: =F95+F96+F97 -> 694.42186 | G98: =G95+G96+G97 -> 640.83304 | H98: =H95+H96+H97 -> 578.1841 | I98: =I95+I96+I97 -> 589.73094 | J98: =J95+J96+J97 -> 601.70805 | ... L98: =L95+L96+L97 -> 627.11194
A99: EBITDA margin | C99: =C98/C95 -> 0.66010588 | D99: =D98/D95 -> 0.68373966 | E99: =E98/E95 -> 0.74087628 | F99: =F98/F95 -> 0.70430964 | G99: =G98/G95 -> 0.67571603 | H99: =H98/H95 -> 0.64023404 | I99: =I98/I95 -> 0.63175499 | J99: =J98/J95 -> 0.62290758 | ... L99: =L98/L95 -> 0.6040913
A100: D&A | C100: =-Inputs!$B$34 -> -30 | D100: =-Inputs!$B$34 -> -30 | E100: =-Inputs!$B$34 -> -30 | F100: =-Inputs!$B$34 -> -30 | G100: =-Inputs!$B$34 -> -30 | H100: =-Inputs!$B$34 -> -30 | I100: =-Inputs!$B$34 -> -30 | J100: =-Inputs!$B$34 -> -30 | ... L100: =-Inputs!$B$34 -> -30
A101: EBIT | C101: =C98+C100 -> 456.3 | D101: =D98+D100 -> 538.762 | E101: =E98+E100 -> 761.29054 | F101: =F98+F100 -> 664.42186 | G101: =G98+G100 -> 610.83304 | H101: =H98+H100 -> 548.1841 | I101: =I98+I100 -> 559.73094 | J101: =J98+J100 -> 571.70805 | ... L101: =L98+L100 -> 597.11194
A102: Taxes | C102: =-C101*Inputs!$B$17 -> -73.008 | D102: =-D101*Inputs!$B$17 -> -86.20192 | E102: =-E101*Inputs!$B$17 -> -121.80649 | F102: =-F101*Inputs!$B$17 -> -106.3075 | G102: =-G101*Inputs!$B$17 -> -97.733287 | H102: =-H101*Inputs!$B$17 -> -87.709457 | I102: =-I101*Inputs!$B$17 -> -89.55695 | J102: =-J101*Inputs!$B$17 -> -91.473288 | ... L102: =-L101*Inputs!$B$17 -> -95.537911
A103: NOPAT | C103: =C101+C102 -> 383.292 | D103: =D101+D102 -> 452.56008 | E103: =E101+E102 -> 639.48405 | F103: =F101+F102 -> 558.11436 | G103: =G101+G102 -> 513.09975 | H103: =H101+H102 -> 460.47465 | I103: =I101+I102 -> 470.17399 | J103: =J101+J102 -> 480.23476 | ... L103: =L101+L102 -> 501.57403
A104: Capex | C104: =-Inputs!$B$35 -> -30 | D104: =-Inputs!$B$35 -> -30 | E104: =-Inputs!$B$35 -> -30 | F104: =-Inputs!$B$35 -> -30 | G104: =-Inputs!$B$35 -> -30 | H104: =-Inputs!$B$35 -> -30 | I104: =-Inputs!$B$35 -> -30 | J104: =-Inputs!$B$35 -> -30 | ... L104: =-Inputs!$B$35 -> -30
A105: Change in NWC | C105: =0 -> 0 | D105: =-Inputs!$B$36*(D95-C95) -> -9.514 | E105: =-Inputs!$B$36*(E95-D95) -> -23.62068 | F105: =-Inputs!$B$36*(F95-E95) -> 8.2085764 | G105: =-Inputs!$B$36*(G95-F95) -> 3.7584783 | H105: =-Inputs!$B$36*(H95-G95) -> 4.5293839 | I105: =-Inputs!$B$36*(I95-H95) -> -3.039804 | J105: =-Inputs!$B$36*(J95-I95) -> -3.2486368 | K105: =-Inputs!$B$36*(K95-J95) -> -3.4794106 | L105: =-Inputs!$B$36*(L95-K95) -> -3.7346961
A106: Free cash flow | C106: =C103-C100+C104+C105 -> 383.292 | D106: =D103-D100+D104+D105 -> 443.04608 | E106: =E103-E100+E104+E105 -> 615.86337 | F106: =F103-F100+F104+F105 -> 566.32294 | G106: =G103-G100+G104+G105 -> 516.85823 | H106: =H103-H100+H104+H105 -> 465.00403 | I106: =I103-I100+I104+I105 -> 467.13418 | J106: =J103-J100+J104+J105 -> 476.98613 | ... L106: =L103-L100+L104+L105 -> 497.83934
A107: Discount period (years) | D107: 1 | E107: 2 | F107: 3 | G107: 4 | H107: 5 | I107: 6 | J107: 7 | K107: 8 | L107: 9
...

Sheet Reverse DCF
A1: What do you have to believe? Orders a year (LNG-carrier equivalents, 2027-35) that justify the price; everything else as in the base case.
A2: Value is linear in orders, so it is solved exactly from two helper DCFs (0 and 1 order a year).
A4: Target equity value (price x shares) | C4: =Inputs!B18 -> 7843.3772
A5: Equity value with 0 orders a year | C5: =DCF!C161 -> -252.42662
A6: Extra equity value per order a year | C6: =DCF!C202-DCF!C161 -> 84.088732
A7: Implied orders a year, 2027-2035 | C7: =(C4-C5)/C6 -> 96.276916
A8: Base case assumption | C8: =Inputs!D50 -> 60
A9: Company 10-year estimate (c.550 LNGC + other units, per year) | C9: 60
A12: Free cash flow rows used by the grid (€mm)
C13: 2027 | D13: 2028 | E13: 2029 | F13: 2030 | G13: 2031 | H13: 2032 | I13: 2033 | J13: 2034 | K13: 2035
A14: F0: FCF with 0 orders a year | C14: =DCF!D149 -> 428.84272 | D14: =DCF!E149 -> 467.14398 | E14: =DCF!F149 -> 122.35405 | F14: =DCF!G149 -> -90.149859 | G14: =DCF!H149 -> -170.61623 | H14: =DCF!I149 -> -182.0442 | I14: =DCF!J149 -> -186.15852 | J14: =DCF!K149 -> -190.33654 | K14: =DCF!L149 -> -194.57513
A15: dF: FCF per order a year | C15: =DCF!D190-DCF!D149 -> 0 | D15: =DCF!E190-DCF!E149 -> 1.43412 | E15: =DCF!F190-DCF!F149 -> 5.6004324 | F15: =DCF!G190-DCF!G149 -> 8.038041 | G15: =DCF!H190-DCF!H149 -> 8.4410519 | H15: =DCF!I190-DCF!I149 -> 8.6098729 | I15: =DCF!J190-DCF!J149 -> 8.7820704 | J15: =DCF!K190-DCF!K149 -> 8.9577118 | K15: =DCF!L190-DCF!L149 -> 9.136866
A16: Discount period | C16: 1 | D16: 2 | E16: 3 | F16: 4 | G16: 5 | H16: 6 | I16: 7 | J16: 8 | K16: 9
A19: Value per share (€): WACC (rows) x new orders a year 2027-35 (columns)
A20: WACC \ orders | C20: 30 | D20: 40 | E20: 50 | F20: 60 | G20: 70 | H20: 80 | I20: 90
A21: 0.075 | C21: =(SUMPRODUCT(($C$14:$K$14+C$20*$C$15:$K$15)/(1+$A21)^$C$16:$K$16)+($K$14+C$20*$K$15)*(1+Inputs!$C$52)/($A21-Inputs!$C$52)/(1+$A21)^$K$16+(Inputs!$B$9+DCF!C160))/Inputs!$B$6 -> 70.527837 | D21: =(SUMPRODUCT(($C$14:$K$14+D$20*$C$15:$K$15)/(1+$A21)^$C$16:$K$16)+($K$14+D$20*$K$15)*(1+Inputs!$C$52)/($A21-Inputs!$C$52)/(1+$A21)^$K$16+(Inputs!$B$9+DCF!C160))/Inputs!$B$6 -> 102.61216 | E21: =(SUMPRODUCT(($C$14:$K$14+E$20*$C$15:$K$15)/(1+$A21)^$C$16:$K$16)+($K$14+E$20*$K$15)*(1+Inputs!$C$52)/($A21-Inputs!$C$52)/(1+$A21)^$K$16+(Inputs!$B$9+DCF!C160))/Inputs!$B$6 -> 134.69648 | F21: =(SUMPRODUCT(($C$14:$K$14+F$20*$C$15:$K$15)/(1+$A21)^$C$16:$K$16)+($K$14+F$20*$K$15)*(1+Inputs!$C$52)/($A21-Inputs!$C$52)/(1+$A21)^$K$16+(Inputs!$B$9+DCF!C160))/Inputs!$B$6 -> 166.78081 | G21: =(SUMPRODUCT(($C$14:$K$14+G$20*$C$15:$K$15)/(1+$A21)^$C$16:$K$16)+($K$14+G$20*$K$15)*(1+Inputs!$C$52)/($A21-Inputs!$C$52)/(1+$A21)^$K$16+(Inputs!$B$9+DCF!C160))/Inputs!$B$6 -> 198.86513 | H21: =(SUMPRODUCT(($C$14:$K$14+H$20*$C$15:$K$15)/(1+$A21)^$C$16:$K$16)+($K$14+H$20*$K$15)*(1+Inputs!$C$52)/($A21-Inputs!$C$52)/(1+$A21)^$K$16+(Inputs!$B$9+DCF!C160))/Inputs!$B$6 -> 230.94945 | I21: =(SUMPRODUCT(($C$14:$K$14+I$20*$C$15:$K$15)/(1+$A21)^$C$16:$K$16)+($K$14+I$20*$K$15)*(1+Inputs!$C$52)/($A21-Inputs!$C$52)/(1+$A21)^$K$16+(Inputs!$B$9+DCF!C160))/Inputs!$B$6 -> 263.03377
A22: 0.08 | C22: =(SUMPRODUCT(($C$14:$K$14+C$20*$C$15:$K$15)/(1+$A22)^$C$16:$K$16)+($K$14+C$20*$K$15)*(1+Inputs!$C$52)/($A22-Inputs!$C$52)/(1+$A22)^$K$16+(Inputs!$B$9+DCF!C160))/Inputs!$B$6 -> 67.852274 | D22: =(SUMPRODUCT(($C$14:$K$14+D$20*$C$15:$K$15)/(1+$A22)^$C$16:$K$16)+($K$14+D$20*$K$15)*(1+Inputs!$C$52)/($A22-Inputs!$C$52)/(1+$A22)^$K$16+(Inputs!$B$9+DCF!C160))/Inputs!$B$6 -> 97.167283 | E22: =(SUMPRODUCT(($C$14:$K$14+E$20*$C$15:$K$15)/(1+$A22)^$C$16:$K$16)+($K$14+E$20*$K$15)*(1+Inputs!$C$52)/($A22-Inputs!$C$52)/(1+$A22)^$K$16+(Inputs!$B$9+DCF!C160))/Inputs!$B$6 -> 126.48229 | F22: =(SUMPRODUCT(($C$14:$K$14+F$20*$C$15:$K$15)/(1+$A22)^$C$16:$K$16)+($K$14+F$20*$K$15)*(1+Inputs!$C$52)/($A22-Inputs!$C$52)/(1+$A22)^$K$16+(Inputs!$B$9+DCF!C160))/Inputs!$B$6 -> 155.7973 | G22: =(SUMPRODUCT(($C$14:$K$14+G$20*$C$15:$K$15)/(1+$A22)^$C$16:$K$16)+($K$14+G$20*$K$15)*(1+Inputs!$C$52)/($A22-Inputs!$C$52)/(1+$A22)^$K$16+(Inputs!$B$9+DCF!C160))/Inputs!$B$6 -> 185.11231 | H22: =(SUMPRODUCT(($C$14:$K$14+H$20*$C$15:$K$15)/(1+$A22)^$C$16:$K$16)+($K$14+H$20*$K$15)*(1+Inputs!$C$52)/($A22-Inputs!$C$52)/(1+$A22)^$K$16+(Inputs!$B$9+DCF!C160))/Inputs!$B$6 -> 214.42732 | I22: =(SUMPRODUCT(($C$14:$K$14+I$20*$C$15:$K$15)/(1+$A22)^$C$16:$K$16)+($K$14+I$20*$K$15)*(1+Inputs!$C$52)/($A22-Inputs!$C$52)/(1+$A22)^$K$16+(Inputs!$B$9+DCF!C160))/Inputs!$B$6 -> 243.74233
A23: 0.085 | C23: =(SUMPRODUCT(($C$14:$K$14+C$20*$C$15:$K$15)/(1+$A23)^$C$16:$K$16)+($K$14+C$20*$K$15)*(1+Inputs!$C$52)/($A23-Inputs!$C$52)/(1+$A23)^$K$16+(Inputs!$B$9+DCF!C160))/Inputs!$B$6 -> 65.529192 | D23: =(SUMPRODUCT(($C$14:$K$14+D$20*$C$15:$K$15)/(1+$A23)^$C$16:$K$16)+($K$14+D$20*$K$15)*(1+Inputs!$C$52)/($A23-Inputs!$C$52)/(1+$A23)^$K$16+(Inputs!$B$9+DCF!C160))/Inputs!$B$6 -> 92.475107 | E23: =(SUMPRODUCT(($C$14:$K$14+E$20*$C$15:$K$15)/(1+$A23)^$C$16:$K$16)+($K$14+E$20*$K$15)*(1+Inputs!$C$52)/($A23-Inputs!$C$52)/(1+$A23)^$K$16+(Inputs!$B$9+DCF!C160))/Inputs!$B$6 -> 119.42102 | F23: =(SUMPRODUCT(($C$14:$K$14+F$20*$C$15:$K$15)/(1+$A23)^$C$16:$K$16)+($K$14+F$20*$K$15)*(1+Inputs!$C$52)/($A23-Inputs!$C$52)/(1+$A23)^$K$16+(Inputs!$B$9+DCF!C160))/Inputs!$B$6 -> 146.36694 | G23: =(SUMPRODUCT(($C$14:$K$14+G$20*$C$15:$K$15)/(1+$A23)^$C$16:$K$16)+($K$14+G$20*$K$15)*(1+Inputs!$C$52)/($A23-Inputs!$C$52)/(1+$A23)^$K$16+(Inputs!$B$9+DCF!C160))/Inputs!$B$6 -> 173.31285 | H23: =(SUMPRODUCT(($C$14:$K$14+H$20*$C$15:$K$15)/(1+$A23)^$C$16:$K$16)+($K$14+H$20*$K$15)*(1+Inputs!$C$52)/($A23-Inputs!$C$52)/(1+$A23)^$K$16+(Inputs!$B$9+DCF!C160))/Inputs!$B$6 -> 200.25877 | I23: =(SUMPRODUCT(($C$14:$K$14+I$20*$C$15:$K$15)/(1+$A23)^$C$16:$K$16)+($K$14+I$20*$K$15)*(1+Inputs!$C$52)/($A23-Inputs!$C$52)/(1+$A23)^$K$16+(Inputs!$B$9+DCF!C160))/Inputs!$B$6 -> 227.20468
A24: 0.09 | C24: =(SUMPRODUCT(($C$14:$K$14+C$20*$C$15:$K$15)/(1+$A24)^$C$16:$K$16)+($K$14+C$20*$K$15)*(1+Inputs!$C$52)/($A24-Inputs!$C$52)/(1+$A24)^$K$16+(Inputs!$B$9+DCF!C160))/Inputs!$B$6 -> 63.488743 | D24: =(SUMPRODUCT(($C$14:$K$14+D$20*$C$15:$K$15)/(1+$A24)^$C$16:$K$16)+($K$14+D$20*$K$15)*(1+Inputs!$C$52)/($A24-Inputs!$C$52)/(1+$A24)^$K$16+(Inputs!$B$9+DCF!C160))/Inputs!$B$6 -> 88.385643 | E24: =(SUMPRODUCT(($C$14:$K$14+E$20*$C$15:$K$15)/(1+$A24)^$C$16:$K$16)+($K$14+E$20*$K$15)*(1+Inputs!$C$52)/($A24-Inputs!$C$52)/(1+$A24)^$K$16+(Inputs!$B$9+DCF!C160))/Inputs!$B$6 -> 113.28254 | F24: =(SUMPRODUCT(($C$14:$K$14+F$20*$C$15:$K$15)/(1+$A24)^$C$16:$K$16)+($K$14+F$20*$K$15)*(1+Inputs!$C$52)/($A24-Inputs!$C$52)/(1+$A24)^$K$16+(Inputs!$B$9+DCF!C160))/Inputs!$B$6 -> 138.17944 | G24: =(SUMPRODUCT(($C$14:$K$14+G$20*$C$15:$K$15)/(1+$A24)^$C$16:$K$16)+($K$14+G$20*$K$15)*(1+Inputs!$C$52)/($A24-Inputs!$C$52)/(1+$A24)^$K$16+(Inputs!$B$9+DCF!C160))/Inputs!$B$6 -> 163.07634 | H24: =(SUMPRODUCT(($C$14:$K$14+H$20*$C$15:$K$15)/(1+$A24)^$C$16:$K$16)+($K$14+H$20*$K$15)*(1+Inputs!$C$52)/($A24-Inputs!$C$52)/(1+$A24)^$K$16+(Inputs!$B$9+DCF!C160))/Inputs!$B$6 -> 187.97324 | I24: =(SUMPRODUCT(($C$14:$K$14+I$20*$C$15:$K$15)/(1+$A24)^$C$16:$K$16)+($K$14+I$20*$K$15)*(1+Inputs!$C$52)/($A24-Inputs!$C$52)/(1+$A24)^$K$16+(Inputs!$B$9+DCF!C160))/Inputs!$B$6 -> 212.87014
A25: 0.095 | C25: =(SUMPRODUCT(($C$14:$K$14+C$20*$C$15:$K$15)/(1+$A25)^$C$16:$K$16)+($K$14+C$20*$K$15)*(1+Inputs!$C$52)/($A25-Inputs!$C$52)/(1+$A25)^$K$16+(Inputs!$B$9+DCF!C160))/Inputs!$B$6 -> 61.678528 | D25: =(SUMPRODUCT(($C$14:$K$14+D$20*$C$15:$K$15)/(1+$A25)^$C$16:$K$16)+($K$14+D$20*$K$15)*(1+Inputs!$C$52)/($A25-Inputs!$C$52)/(1+$A25)^$K$16+(Inputs!$B$9+DCF!C160))/Inputs!$B$6 -> 84.786388 | E25: =(SUMPRODUCT(($C$14:$K$14+E$20*$C$15:$K$15)/(1+$A25)^$C$16:$K$16)+($K$14+E$20*$K$15)*(1+Inputs!$C$52)/($A25-Inputs!$C$52)/(1+$A25)^$K$16+(Inputs!$B$9+DCF!C160))/Inputs!$B$6 -> 107.89425 | F25: =(SUMPRODUCT(($C$14:$K$14+F$20*$C$15:$K$15)/(1+$A25)^$C$16:$K$16)+($K$14+F$20*$K$15)*(1+Inputs!$C$52)/($A25-Inputs!$C$52)/(1+$A25)^$K$16+(Inputs!$B$9+DCF!C160))/Inputs!$B$6 -> 131.00211 | G25: =(SUMPRODUCT(($C$14:$K$14+G$20*$C$15:$K$15)/(1+$A25)^$C$16:$K$16)+($K$14+G$20*$K$15)*(1+Inputs!$C$52)/($A25-Inputs!$C$52)/(1+$A25)^$K$16+(Inputs!$B$9+DCF!C160))/Inputs!$B$6 -> 154.10997 | H25: =(SUMPRODUCT(($C$14:$K$14+H$20*$C$15:$K$15)/(1+$A25)^$C$16:$K$16)+($K$14+H$20*$K$15)*(1+Inputs!$C$52)/($A25-Inputs!$C$52)/(1+$A25)^$K$16+(Inputs!$B$9+DCF!C160))/Inputs!$B$6 -> 177.21783 | I25: =(SUMPRODUCT(($C$14:$K$14+I$20*$C$15:$K$15)/(1+$A25)^$C$16:$K$16)+($K$14+I$20*$K$15)*(1+Inputs!$C$52)/($A25-Inputs!$C$52)/(1+$A25)^$K$16+(Inputs!$B$9+DCF!C160))/Inputs!$B$6 -> 200.32569
A26: 0.1 | C26: =(SUMPRODUCT(($C$14:$K$14+C$20*$C$15:$K$15)/(1+$A26)^$C$16:$K$16)+($K$14+C$20*$K$15)*(1+Inputs!$C$52)/($A26-Inputs!$C$52)/(1+$A26)^$K$16+(Inputs!$B$9+DCF!C160))/Inputs!$B$6 -> 60.058457 | D26: =(SUMPRODUCT(($C$14:$K$14+D$20*$C$15:$K$15)/(1+$A26)^$C$16:$K$16)+($K$14+D$20*$K$15)*(1+Inputs!$C$52)/($A26-Inputs!$C$52)/(1+$A26)^$K$16+(Inputs!$B$9+DCF!C160))/Inputs!$B$6 -> 81.591296 | E26: =(SUMPRODUCT(($C$14:$K$14+E$20*$C$15:$K$15)/(1+$A26)^$C$16:$K$16)+($K$14+E$20*$K$15)*(1+Inputs!$C$52)/($A26-Inputs!$C$52)/(1+$A26)^$K$16+(Inputs!$B$9+DCF!C160))/Inputs!$B$6 -> 103.12413 | F26: =(SUMPRODUCT(($C$14:$K$14+F$20*$C$15:$K$15)/(1+$A26)^$C$16:$K$16)+($K$14+F$20*$K$15)*(1+Inputs!$C$52)/($A26-Inputs!$C$52)/(1+$A26)^$K$16+(Inputs!$B$9+DCF!C160))/Inputs!$B$6 -> 124.65697 | G26: =(SUMPRODUCT(($C$14:$K$14+G$20*$C$15:$K$15)/(1+$A26)^$C$16:$K$16)+($K$14+G$20*$K$15)*(1+Inputs!$C$52)/($A26-Inputs!$C$52)/(1+$A26)^$K$16+(Inputs!$B$9+DCF!C160))/Inputs!$B$6 -> 146.18981 | H26: =(SUMPRODUCT(($C$14:$K$14+H$20*$C$15:$K$15)/(1+$A26)^$C$16:$K$16)+($K$14+H$20*$K$15)*(1+Inputs!$C$52)/($A26-Inputs!$C$52)/(1+$A26)^$K$16+(Inputs!$B$9+DCF!C160))/Inputs!$B$6 -> 167.72265 | I26: =(SUMPRODUCT(($C$14:$K$14+I$20*$C$15:$K$15)/(1+$A26)^$C$16:$K$16)+($K$14+I$20*$K$15)*(1+Inputs!$C$52)/($A26-Inputs!$C$52)/(1+$A26)^$K$16+(Inputs!$B$9+DCF!C160))/Inputs!$B$6 -> 189.25549
A27: 0.11 | C27: =(SUMPRODUCT(($C$14:$K$14+C$20*$C$15:$K$15)/(1+$A27)^$C$16:$K$16)+($K$14+C$20*$K$15)*(1+Inputs!$C$52)/($A27-Inputs!$C$52)/(1+$A27)^$K$16+(Inputs!$B$9+DCF!C160))/Inputs!$B$6 -> 57.270532 | D27: =(SUMPRODUCT(($C$14:$K$14+D$20*$C$15:$K$15)/(1+$A27)^$C$16:$K$16)+($K$14+D$20*$K$15)*(1+Inputs!$C$52)/($A27-Inputs!$C$52)/(1+$A27)^$K$16+(Inputs!$B$9+DCF!C160))/Inputs!$B$6 -> 76.159929 | E27: =(SUMPRODUCT(($C$14:$K$14+E$20*$C$15:$K$15)/(1+$A27)^$C$16:$K$16)+($K$14+E$20*$K$15)*(1+Inputs!$C$52)/($A27-Inputs!$C$52)/(1+$A27)^$K$16+(Inputs!$B$9+DCF!C160))/Inputs!$B$6 -> 95.049327 | F27: =(SUMPRODUCT(($C$14:$K$14+F$20*$C$15:$K$15)/(1+$A27)^$C$16:$K$16)+($K$14+F$20*$K$15)*(1+Inputs!$C$52)/($A27-Inputs!$C$52)/(1+$A27)^$K$16+(Inputs!$B$9+DCF!C160))/Inputs!$B$6 -> 113.93872 | G27: =(SUMPRODUCT(($C$14:$K$14+G$20*$C$15:$K$15)/(1+$A27)^$C$16:$K$16)+($K$14+G$20*$K$15)*(1+Inputs!$C$52)/($A27-Inputs!$C$52)/(1+$A27)^$K$16+(Inputs!$B$9+DCF!C160))/Inputs!$B$6 -> 132.82812 | H27: =(SUMPRODUCT(($C$14:$K$14+H$20*$C$15:$K$15)/(1+$A27)^$C$16:$K$16)+($K$14+H$20*$K$15)*(1+Inputs!$C$52)/($A27-Inputs!$C$52)/(1+$A27)^$K$16+(Inputs!$B$9+DCF!C160))/Inputs!$B$6 -> 151.71752 | I27: =(SUMPRODUCT(($C$14:$K$14+I$20*$C$15:$K$15)/(1+$A27)^$C$16:$K$16)+($K$14+I$20*$K$15)*(1+Inputs!$C$52)/($A27-Inputs!$C$52)/(1+$A27)^$K$16+(Inputs!$B$9+DCF!C160))/Inputs!$B$6 -> 170.60692
A29: Current price (€) | C29: =Inputs!B5 -> 211.6
A30: Model WACC | C30: =Inputs!B19 -> 0.09628076
